odoo8_addon_l10n_nl_postcodeapi-8.0.0.2.0.99.dev4-py2.7-nspkg.pth
odoo8_addon_l10n_nl_postcodeapi-8.0.0.2.0.99.dev4.dist-info/DESCRIPTION.rst
odoo8_addon_l10n_nl_postcodeapi-8.0.0.2.0.99.dev4.dist-info/METADATA
odoo8_addon_l10n_nl_postcodeapi-8.0.0.2.0.99.dev4.dist-info/RECORD
odoo8_addon_l10n_nl_postcodeapi-8.0.0.2.0.99.dev4.dist-info/WHEEL
odoo8_addon_l10n_nl_postcodeapi-8.0.0.2.0.99.dev4.dist-info/metadata.json
odoo8_addon_l10n_nl_postcodeapi-8.0.0.2.0.99.dev4.dist-info/namespace_packages.txt
odoo8_addon_l10n_nl_postcodeapi-8.0.0.2.0.99.dev4.dist-info/top_level.txt
odoo_addons/l10n_nl_postcodeapi/README.rst
odoo_addons/l10n_nl_postcodeapi/__init__.py
odoo_addons/l10n_nl_postcodeapi/__openerp__.py
odoo_addons/l10n_nl_postcodeapi/data/ir_config_parameter.xml
odoo_addons/l10n_nl_postcodeapi/data/res.country.state.csv
odoo_addons/l10n_nl_postcodeapi/i18n/l10n_nl_postcodeapi.pot
odoo_addons/l10n_nl_postcodeapi/i18n/nl.po
odoo_addons/l10n_nl_postcodeapi/models/__init__.py
odoo_addons/l10n_nl_postcodeapi/models/ir_config_parameter.py
odoo_addons/l10n_nl_postcodeapi/models/res_country_state.py
odoo_addons/l10n_nl_postcodeapi/models/res_partner.py
odoo_addons/l10n_nl_postcodeapi/static/description/icon.png
