Metadata-Version: 2.0
Name: odoo8-addon-l10n-nl-postcodeapi
Version: 8.0.0.2.0.99.dev4
Summary: Autocomplete Dutch addresses using PostcodeApi.nu
Home-page: https://github.com/OCA/l10n-netherlands
Author: Therp BV,Odoo Community Association (OCA)
Author-email: support@odoo-community.org
License: AGPL-3
Platform: UNKNOWN
Classifier: Programming Language :: Python
Classifier: Framework :: Odoo
Classifier: License :: OSI Approved :: GNU Affero General Public License v3
Requires-Python: ~=2.7
Requires-Dist: odoo (<9.0a,>=8.0a)
Requires-Dist: odoo8-addon-partner-street-number
Requires-Dist: pyPostcode
